{"data":{"chart":{"zoomType":"xy","type":"column"},"title":{"text":"Top 15 Accounts for L1 & L2 Demand in COMM, CBU and MNT","style":{"fontSize":"15px"}},"credits":{"enabled":false},"xAxis":{"title":{"text":"Account ID"},"categories":["5200832","5200637","5200401","5201324","5201127","5200176","5201895","5200838","5201229","5200147","5201878","5201727","5200906","5200715","5201025","All Others"]},"yAxis":{"title":{"text":"Demand"}},"series":[{"name":"L1 & L2 Demand","data":[2235,1693,1571,1496,1298,1120,1014,882,667,657,643,636,621,611,571,19036]}]}}